<?xml version="1.0" encoding="utf-8"?>
<window>
	<defaultcontrol>-</defaultcontrol>
	<controls>
		<control type="group" id="0">
			<animation effect="slide" end="0,45" time="160" tween="cubic" condition="Window.IsVisible(seekbar) + !Skin.HasSetting(Show_Info_Paused)">Conditional</animation>
			<animation effect="slide" end="0,165" time="160" tween="cubic" condition="[Window.IsVisible(seekbar) + Skin.HasSetting(Show_Info_Paused)] | [Window.IsVisible(fullscreeninfo) + IsEmpty(Window(home).Property(morefullscreeninfo)) + Player.Paused]">Conditional</animation>
			<animation effect="slide" end="0,135" time="160" tween="cubic" condition="!VideoPlayer.Content(LiveTV) + Window.IsVisible(fullscreeninfo) + IsEmpty(Window(home).Property(morefullscreeninfo)) + !Player.Paused">Conditional</animation>
			<!-- codec infos -->
			<control type="image">
			<visible>!VideoPlayer.Content(LiveTV)</visible>
				<left>0</left>
				<top>0</top>
				<width>1920</width>
				<height>340</height>
				<texture flipy="true">views/lowlist_panelback.png</texture>
				<animation effect="fade" start="100" end="80" time="40" condition="true">Conditional</animation>
				<animation effect="slide" end="0,270" time="160" tween="cubic" condition="VideoPlayer.Content(LiveTV) + System.GetBool(pvrplayback.signalquality)">Conditional</animation>
			</control>
			<control type="image">
				<visible>VideoPlayer.Content(LiveTV)</visible>
				<left>0</left>
				<top>-270</top>
				<width>1920</width>
				<height>630</height>
				<texture flipy="true">views/lowlist_panelback.png</texture>
				<animation effect="fade" start="100" end="80" time="40" condition="true">Conditional</animation>
				<animation effect="slide" end="0,270" time="160" tween="cubic" condition="VideoPlayer.Content(LiveTV) + System.GetBool(pvrplayback.signalquality)">Conditional</animation>
			</control>
			<control type="grouplist" id="0">
				<left>30</left>
				<top>0</top>
				<width>1920</width>
				<height>300</height>
				<aligny>top</aligny>
				<itemgap>10</itemgap>
				<control type="label" id="10">
					<description>row 1 label</description>
					<width>1770</width>
					<height>90</height>
					<align>left</align>
					<aligny>center</aligny>
					<font>Font_Reg28</font>
					<textcolor>grey2</textcolor>
					<label>-</label>
				</control>
				<control type="label" id="11">
					<description>row 2 label</description>
					<width>1770</width>
					<height>90</height>
					<align>left</align>
					<aligny>center</aligny>
					<font>Font_Reg28</font>
					<label>-</label>
					<textcolor>grey2</textcolor>
				</control>
				<control type="label" id="12">
					<description>row 3 label</description>
					<width>1770</width>
					<height>90</height>
					<align>left</align>
					<aligny>center</aligny>
					<font>Font_Reg28</font>
					<label>-</label>
					<textcolor>grey2</textcolor>
				</control>
			</control>
		    <control type="group">
				<left>-20</left>
				<top>320</top>
				<visible>VideoPlayer.Content(LiveTV) + System.GetBool(pvrplayback.signalquality)</visible>
				<control type="label">
					<description>Header</description>
					<left>50</left>
					<top>5</top>
					<width>1200</width>
					<height>25</height>
					<align>left</align>
					<aligny>center</aligny>
					<label>$LOCALIZE[19005]</label>
					<font>Font_Reg33_Caps</font>
					<textcolor>$VAR[FontColorVar]</textcolor>
				</control>
				<control type="label">
					<description>Backend</description>
					<left>50</left>
					<top>40</top>
					<width>250</width>
					<height>25</height>
					<align>left</align>
					<aligny>center</aligny>
					<label>$LOCALIZE[19012]:</label>
					<font>Font_Reg28</font>
					<textcolor>grey2</textcolor>
				</control>
				<control type="label">
					<description>Backend value</description>
					<left>270</left>
					<top>40</top>
					<width>1000</width>
					<height>25</height>
					<align>left</align>
					<aligny>center</aligny>
					<label>$INFO[PVR.ActStreamClient]</label>
					<font>Font_Reg28</font>
					<textcolor>white</textcolor>
				</control>
				<control type="label">
					<description>Device</description>
					<left>50</left>
					<top>70</top>
					<width>250</width>
					<height>25</height>
					<align>left</align>
					<aligny>center</aligny>
					<label>$LOCALIZE[19006]:</label>
					<font>Font_Reg28</font>
					<textcolor>grey2</textcolor>
				</control>
				<control type="label">
					<description>Device value</description>
					<left>270</left>
					<top>70</top>
					<width>1000</width>
					<height>25</height>
					<align>left</align>
					<aligny>center</aligny>
					<label>$INFO[PVR.ActStreamDevice]</label>
					<font>Font_Reg28</font>
					<textcolor>white</textcolor>
				</control>
				<control type="label">
					<description>Status</description>
					<left>50</left>
					<top>100</top>
					<width>250</width>
					<height>25</height>
					<align>left</align>
					<aligny>center</aligny>
					<label>$LOCALIZE[19007]:</label>
					<font>Font_Reg28</font>
					<textcolor>grey2</textcolor>
				</control>
				<control type="label">
					<description>Status value</description>
					<left>270</left>
					<top>100</top>
					<width>1000</width>
					<height>25</height>
					<align>left</align>
					<aligny>center</aligny>
					<label>$INFO[PVR.ActStreamStatus]</label>
					<font>Font_Reg28</font>
					<textcolor>white</textcolor>
				</control>
				<control type="label">
					<description>Signal</description>
					<left>50</left>
					<top>130</top>
					<width>250</width>
					<height>25</height>
					<align>left</align>
					<aligny>center</aligny>
					<label>$LOCALIZE[19008]:</label>
					<font>Font_Reg28</font>
					<textcolor>grey2</textcolor>
				</control>
				<control type="progress">
					<description>Progressbar</description>
					<posx>270</posx>
					<posy>137</posy>
					<width>910</width>
					<height>14</height>
					<info>PVR.ActStreamProgrSignal</info>
				</control>
				<control type="label">
					<description>Signal value</description>
					<left>1210</left>
					<top>135</top>
					<width>180</width>
					<height>25</height>
					<align>left</align>
					<aligny>center</aligny>
					<label>$INFO[PVR.ActStreamSignal]</label>
					<font>Font_Reg28</font>
					<textcolor>white</textcolor>
				</control>
				<control type="label">
					<description>SNR</description>
					<left>50</left>
					<top>160</top>
					<width>250</width>
					<height>25</height>
					<align>left</align>
					<aligny>center</aligny>
					<label>$LOCALIZE[19009]:</label>
					<font>Font_Reg28</font>
					<textcolor>grey2</textcolor>
				</control>
				<control type="progress">
					<description>Progressbar</description>
					<posx>270</posx>
					<posy>167</posy>
					<width>910</width>
					<height>14</height>
					<info>PVR.ActStreamProgrSNR</info>
				</control>
				<control type="label">
					<description>SNR value</description>
					<left>1210</left>
					<top>160</top>
					<width>180</width>
					<height>25</height>
					<align>left</align>
					<aligny>center</aligny>
					<label>$INFO[PVR.ActStreamSNR]</label>
					<font>Font_Reg28</font>
					<textcolor>white</textcolor>
				</control>
				<control type="label">
					<description>BER</description>
					<left>50</left>
					<top>190</top>
					<width>250</width>
					<height>25</height>
					<align>left</align>
					<aligny>center</aligny>
					<label>$LOCALIZE[19010]:</label>
					<font>Font_Reg28</font>
					<textcolor>grey2</textcolor>
				</control>
				<control type="label">
					<description>BER value</description>
					<left>270</left>
					<top>190</top>
					<width>1000</width>
					<height>25</height>
					<align>left</align>
					<aligny>center</aligny>
					<label>$INFO[PVR.ActStreamBER]</label>
					<font>Font_Reg28</font>
					<textcolor>white</textcolor>
				</control>
				<control type="label">
					<description>UNC</description>
					<left>480</left>
					<top>190</top>
					<width>165</width>
					<height>25</height>
					<align>left</align>
					<aligny>center</aligny>
					<label>$LOCALIZE[19011]:</label>
					<font>Font_Reg28</font>
					<textcolor>grey2</textcolor>
				</control>
				<control type="label">
					<description>UNC value</description>
					<left>650</left>
					<top>190</top>
					<width>1000</width>
					<height>25</height>
					<align>left</align>
					<aligny>center</aligny>
					<label>$INFO[PVR.ActStreamUNC]</label>
					<font>Font_Reg28</font>
					<textcolor>white</textcolor>
				</control>
				<control type="label">
					<description>Encryption</description>
					<left>50</left>
					<top>220</top>
					<width>250</width>
					<height>25</height>
					<align>left</align>
					<aligny>center</aligny>
					<label>$LOCALIZE[19015]:</label>
					<font>Font_Reg28</font>
					<textcolor>grey2</textcolor>
				</control>
				<control type="label">
					<description>Encryption value</description>
					<left>270</left>
					<top>220</top>
					<width>1000</width>
					<height>25</height>
					<align>left</align>
					<aligny>center</aligny>
					<label>$INFO[PVR.ActStreamEncryptionName]</label>
					<font>Font_Reg28</font>
					<textcolor>white</textcolor>
				</control>
			</control>
		</control>
		<control type="group" id="1">
			<animation type="WindowOpen">
				<effect type="fade" time="160" end="100"/>
				<effect type="slide" time="160" start="0,-98" end="0,0" tween="cubic"/>
			</animation>
			<animation type="WindowClose">
				<effect type="fade" time="160" start="100" end="0"/>
				<effect type="slide" time="160" end="0,-98" easing="in" tween="cubic"/>
			</animation>
			<animation type="Visible">
				<effect type="fade" time="160" end="100"/>
				<effect type="slide" time="160" start="0,-98" end="0,0" tween="cubic"/>
			</animation>
			<animation type="Hidden">
				<effect type="fade" time="160" start="100" end="0"/>
				<effect type="slide" time="160" end="0,-98" easing="in" tween="cubic"/>
			</animation>
			<visible>![Player.Forwarding|Player.Seeking] + ![Window.IsVisible(seekbar) | Window.IsVisible(fullscreeninfo)]</visible>
			<visible>!VideoPlayer.Content(LiveTV)</visible>
			<control type="image" id="1">
				<posx>704</posx>
				<width>513</width>
				<height>87</height>
				<texture flipy="true">osd/osd_top_bar.png</texture>
				<visible>[[Player.Paused + !Player.Caching] + !Player.Seeking + !Player.DisplayAfterSeek] | [[Player.Paused + Player.Caching] + !Player.Seeking] | Player.Seeking|[Player.DisplayAfterSeek + ![player.forwarding | player.rewinding] + !IsEmpty(Player.SeekOffset)]</visible>
			</control>
			<control type="label" id="1">
				<posx>750</posx>
				<width>420</width>
				<height>42</height>
				<align>center</align>
				<label>$LOCALIZE[15107] $INFO[Player.CacheLevel]%</label>
				<font>Font_Reg33_Caps</font>
				<shadowcolor>88e5e5e5</shadowcolor>
				<textcolor>FF363636</textcolor>
				<visible>[Player.Paused + Player.Caching] + !Player.Seeking</visible>
			</control>
		</control>
		<control type="group" id="2">
			<visible>[Player.ShowInfo|Player.Forwarding|Player.Seeking] + ![Window.IsVisible(fullscreeninfo) | Window.IsVisible(osdvideosettings) | Window.IsVisible(osdaudiosettings) | Window.IsVisible(videobookmarks) | Window.IsVisible(PVROSDChannels) | Window.IsVisible(PVROSDGuide)]</visible>
			<visible>VideoPlayer.Content(LiveTV) + !IsEmpty(VideoPlayer.ChannelName)</visible>
			<include condition="IsEmpty(Skin.String(LiveTV.InfobarType)) | StringCompare(Skin.String(LiveTV.InfobarType),2)">FullScreenInfoBarLiveTV</include>
			<include condition="StringCompare(Skin.String(LiveTV.InfobarType),1)">FullScreenInfoBarLiveTV_Compact</include>
		</control>
	</controls>
</window>
