<?xml version='1.0' encoding='UTF-8'?>
<shortcuts>
	<shortcut>
		<defaultID>movies</defaultID>
		<label>342</label>
		<label2>Common menu item</label2>
		<icon>special://skin/extras/BigIcons/Film.png</icon>
		<action>ActivateWindow(Videos,videodb://movies/titles/,return)</action>
	</shortcut>
	<shortcut>
		<defaultID>tvshows</defaultID>
		<label>20343</label>
		<label2>Common menu item</label2>
		<icon>special://skin/extras/BigIcons/Television.png</icon>
		<action>ActivateWindow(Videos,videodb://tvshows/titles/,return)</action>
	</shortcut>
	<shortcut>
		<defaultID>music</defaultID>
		<label>10005</label>
		<label2>Common menu item</label2>
		<icon>special://skin/extras/BigIcons/Headphone.png</icon>
		<action>ActivateWindow(Music)</action>
	</shortcut>
	<shortcut>
		<defaultID>musicvideos</defaultID>
		<label>20389</label>
		<label2>Common menu item</label2>
		<icon>special://skin/extras/BigIcons/Media.png</icon>
		<action>ActivateWindow(Videos,videodb://musicvideos/titles/,return)</action>
	</shortcut>
	<shortcut>
		<defaultID>livetv</defaultID>
		<label>32022</label>
		<label2>Common menu item</label2>
		<icon>special://skin/extras/BigIcons/TV.png</icon>
		<action>ActivateWindow(TVGuide)</action>
	</shortcut>
	<shortcut>
		<defaultID>1037</defaultID>
		<label>1037</label>
		<label2>Videos</label2>
		<icon>special://skin/extras/BigIcons/Camcorder.png</icon>
		<action>ActivateWindow(Videos,Addons,return)</action>
	</shortcut>
	<shortcut>
		<defaultID>programs</defaultID>
		<label>10001</label>
		<label2>Programs</label2>
		<icon>special://skin/extras/BigIcons/Puzzle.png</icon>
		<action>ActivateWindow(Programs,Addons,return)</action>
	</shortcut>
	<shortcut>
		<defaultID>script.globalsearch</defaultID>
		<label>137</label>
		<label2>Program</label2>
		<icon>special://skin/extras/BigIcons/Search.png</icon>
		<action>RunAddOn(script.globalsearch)</action>
	</shortcut>
	<shortcut>
		<defaultID>1036</defaultID>
		<label>1036</label>
		<label2>Common menu item</label2>
		<icon>special://skin/extras/BigIcons/Star.png</icon>
		<action>ActivateWindow(Favourites)</action>
	</shortcut>
</shortcuts>
